<rules title="finish" language="fi">
	<rule name="requiredcond"><![CDATA[T&auml;m&auml; kentt&auml; on pakollinen!]]></rule>
	<rule name="remotecond"><![CDATA[Sy&ouml;tetty tieto ei ole kelvollinen.]]></rule>
	<rule name="emailcond"><![CDATA[Sy&ouml;t&auml; s&auml;hk&ouml;postiosoite oikeassa muodossa.]]></rule>
	<rule name="urlcond"><![CDATA[Sy&ouml;t&auml; URL-osoite oikeassa muodossa.]]></rule>
	<rule name="datecond"><![CDATA[Sy&ouml;t&auml; p&auml;iv&auml;m&auml;&auml;r&auml; kelvollisessa muodossa.]]></rule>
	<rule name="dateDEcond"><![CDATA[Sy&ouml;t&auml; p&auml;iv&auml;m&auml;&auml;r&auml; kelvollisessa muodossa (dd.mm.yyyy).]]></rule>
	<rule name="dateisocond"><![CDATA[Sy&ouml;t&auml; p&auml;iv&auml;m&auml;&auml;r&auml; kelvollisessa muodossa (ISO).]]></rule>
	<rule name="numbercond"><![CDATA[Sy&ouml;t&auml; numero kelvollisessa muodossa.]]></rule>
	<rule name="numbercompcond"><![CDATA[Sy&ouml;t&auml; numero kelvollisessa muodossa.]]></rule>
	<rule name="digitscond"><![CDATA[Sy&ouml;t&auml; luku kelvollisessa muodossa.]]></rule>
	<rule name="equalTocond"><![CDATA[Sy&ouml;t&auml; sama arvo uudelleen .]]></rule>
	<rule name="notEqualTocond"><![CDATA[&auml;l&auml; kirjoita samaa arvoa uudelleen ({0}).]]></rule>
	<rule name="acceptcond"><![CDATA[Sy&ouml;t&auml; kelvollinen tiedostop&auml;&auml;te.]]></rule>
	<rule name="maxlengthcond"><![CDATA[Sy&ouml;t&auml; korkeintaan {0} merkki&auml;.]]></rule>
	<rule name="minlengthcond"><![CDATA[Sy&ouml;t&auml; korkeintaan {0} merkki&auml;.]]></rule>
	<rule name="rangelengthcond"><![CDATA[Sy&ouml;tettyjen merkkien m&auml;&auml;r&auml; tulee olla v&auml;hint&auml;&auml;n {0} ja korkeintaan {1}.]]></rule>
	<rule name="rangecond"><![CDATA[Sy&ouml;tetyn arvon tulee olla v&auml;lill&auml; {0} ja {1}.]]></rule>
	<rule name="maxcond"><![CDATA[Anna arvo, joka on pienempi tai yht&auml;suuri kuin {0}.]]></rule>
	<rule name="mincond"><![CDATA[Anna arvo, joka on suurempi tai yht&auml;suuri kuin {0}.]]></rule>
	<rule name="mastercardcond"><![CDATA[Sy&ouml;t&auml; kelvollinen MasterCard korttinumero.]]></rule>
	<rule name="visacardcond"><![CDATA[Sy&ouml;t&auml; kelvollinen Visa korttinumero.]]></rule>
	<rule name="americanexpcond"><![CDATA[Sy&ouml;t&auml; kelvollinen American Express korttinumero.]]></rule>
	<rule name="dinerscardcond"><![CDATA[Sy&ouml;t&auml; kelvollinen Diners Club korttinumero.]]></rule>
	<rule name="discovercardcond"><![CDATA[Sy&ouml;t&auml; kelvollinen Discover korttinumero.]]></rule>
	<rule name="jcbcardcond"><![CDATA[Sy&ouml;t&auml; kelvollinen JCB korttinumero.]]></rule>	
	<rule name="ajaxexistscond"><![CDATA[Kentt&auml;&auml;n sy&ouml;tetty arvo ei ole kelvollinen.]]></rule>
	<rule name="ibancond"><![CDATA[Anna oikea IBAN numero.]]></rule>
	<rule name="vatcond"><![CDATA[Anna oikea VAT numero.]]></rule>	
	<rule name="minrequiredcond"><![CDATA[Valitse v&auml;hint&auml;&auml;n {0} tuotetta.]]></rule>
	<rule name="maxrequiredcond"><![CDATA[Valitse korkeintaan {0} tuotetta.]]></rule>
	<rule name="creditcardcond"><![CDATA[Anna voimassaoleva luottokortin numero.]]></rule>
	<rule name="sessioncond"><![CDATA[Arvo ei vastaa tallennettua arvoa session.]]></rule>
	<rule name="letterscond"><![CDATA[Anna kirjaimet vain.]]></rule>
	<rule name="alphanumericcond"><![CDATA[Kirjoita kirjaimia vain.]]></rule>
	<rule name="alphanumericlatcond"><![CDATA[Anna aakkosnumeerisia ja Latinalaisen merkkej&auml; vain.]]></rule>
	<rule name="charactersetcond"><![CDATA[T&auml;m&auml; kentt&auml; sis&auml;lt&auml;&auml; merkkej&auml;, jotka eiv&auml;t ole sallittuja.]]></rule>
	<rule name="allowedcond"><![CDATA[Ainoastaan merkki {0} on sallittua.]]></rule>
	<rule name="disallowedcond"><![CDATA[Merkkirajoitusta {0} ei ole sallittua.]]></rule>	
	<rule name="forbiddencond"><![CDATA[Kent&#228;ss&#228; roskapostin sanoja]]></rule>
</rules>