<?xml version="1.0" encoding="utf-8" ?>
<dwsync>
<file name="ui-bg_flat_0_aaaaaa_40x100.png" server="172.18.0.178//var/www/mcit_th/" local="129773368459744196" remote="129773372810000000" />
<file name="ui-bg_glass_55_fbf9ee_1x400.png" server="172.18.0.178//var/www/mcit_th/" local="129773368459794156" remote="129773372810000000" />
<file name="ui-bg_glass_65_ffffff_1x400.png" server="172.18.0.178//var/www/mcit_th/" local="129773368459874092" remote="129773372810000000" />
<file name="ui-bg_glass_75_dadada_1x400.png" server="172.18.0.178//var/www/mcit_th/" local="129773368459914060" remote="129773372810000000" />
<file name="ui-bg_glass_75_e6e6e6_1x400.png" server="172.18.0.178//var/www/mcit_th/" local="129773368459954028" remote="129773372810000000" />
<file name="ui-bg_glass_75_ffffff_1x400.png" server="172.18.0.178//var/www/mcit_th/" local="129773368459993996" remote="129773372810000000" />
<file name="ui-bg_highlight-soft_75_cccccc_1x100.png" server="172.18.0.178//var/www/mcit_th/" local="129773368460023972" remote="129773372810000000" />
<file name="ui-bg_inset-soft_95_fef1ec_1x100.png" server="172.18.0.178//var/www/mcit_th/" local="129773368460063940" remote="129773372810000000" />
<file name="ui-icons_222222_256x240.png" server="172.18.0.178//var/www/mcit_th/" local="129773368460283764" remote="129773372810000000" />
<file name="ui-icons_2e83ff_256x240.png" server="172.18.0.178//var/www/mcit_th/" local="129773368460323732" remote="129773372810000000" />
<file name="ui-icons_454545_256x240.png" server="172.18.0.178//var/www/mcit_th/" local="129773368460403668" remote="129773372810000000" />
<file name="ui-icons_888888_256x240.png" server="172.18.0.178//var/www/mcit_th/" local="129773368460453628" remote="129773372810000000" />
<file name="ui-icons_cd0a0a_256x240.png" server="172.18.0.178//var/www/mcit_th/" local="129773368460493596" remote="129773372810000000" />
<file name="ui-bg_flat_0_aaaaaa_40x100.png" server="172.18.0.111//var/www/servicios/" local="129773368459744196" remote="129827749180000000" />
<file name="ui-bg_glass_55_fbf9ee_1x400.png" server="172.18.0.111//var/www/servicios/" local="129773368459794156" remote="129827749180000000" />
<file name="ui-bg_glass_65_ffffff_1x400.png" server="172.18.0.111//var/www/servicios/" local="129773368459874092" remote="129827749180000000" />
<file name="ui-bg_glass_75_dadada_1x400.png" server="172.18.0.111//var/www/servicios/" local="129773368459914060" remote="129827749180000000" />
<file name="ui-bg_glass_75_e6e6e6_1x400.png" server="172.18.0.111//var/www/servicios/" local="129773368459954028" remote="129827749180000000" />
<file name="ui-bg_glass_75_ffffff_1x400.png" server="172.18.0.111//var/www/servicios/" local="129773368459993996" remote="129827749180000000" />
<file name="ui-bg_highlight-soft_75_cccccc_1x100.png" server="172.18.0.111//var/www/servicios/" local="129773368460023972" remote="129827749180000000" />
<file name="ui-bg_inset-soft_95_fef1ec_1x100.png" server="172.18.0.111//var/www/servicios/" local="129773368460063940" remote="129827749180000000" />
<file name="ui-icons_222222_256x240.png" server="172.18.0.111//var/www/servicios/" local="129773368460283764" remote="129827749180000000" />
<file name="ui-icons_2e83ff_256x240.png" server="172.18.0.111//var/www/servicios/" local="129773368460323732" remote="129827749180000000" />
<file name="ui-icons_454545_256x240.png" server="172.18.0.111//var/www/servicios/" local="129773368460403668" remote="129827749180000000" />
<file name="ui-icons_888888_256x240.png" server="172.18.0.111//var/www/servicios/" local="129773368460453628" remote="129827749180000000" />
<file name="ui-icons_cd0a0a_256x240.png" server="172.18.0.111//var/www/servicios/" local="129773368460493596" remote="129827749180000000" />
<file name="ui-bg_flat_0_aaaaaa_40x100.png" server="172.18.0.178//var/www/it_atenea/" local="129773368459744196" remote="129895236280000000" />
<file name="ui-bg_glass_55_fbf9ee_1x400.png" server="172.18.0.178//var/www/it_atenea/" local="129773368459794156" remote="129895236280000000" />
<file name="ui-bg_glass_65_ffffff_1x400.png" server="172.18.0.178//var/www/it_atenea/" local="129773368459874092" remote="129895236280000000" />
<file name="ui-bg_glass_75_dadada_1x400.png" server="172.18.0.178//var/www/it_atenea/" local="129773368459914060" remote="129895236280000000" />
<file name="ui-bg_glass_75_e6e6e6_1x400.png" server="172.18.0.178//var/www/it_atenea/" local="129773368459954028" remote="129895236280000000" />
<file name="ui-bg_glass_75_ffffff_1x400.png" server="172.18.0.178//var/www/it_atenea/" local="129773368459993996" remote="129895236280000000" />
<file name="ui-bg_highlight-soft_75_cccccc_1x100.png" server="172.18.0.178//var/www/it_atenea/" local="129773368460023972" remote="129895236280000000" />
<file name="ui-bg_inset-soft_95_fef1ec_1x100.png" server="172.18.0.178//var/www/it_atenea/" local="129773368460063940" remote="129895236280000000" />
<file name="ui-icons_222222_256x240.png" server="172.18.0.178//var/www/it_atenea/" local="129773368460283764" remote="129895236280000000" />
<file name="ui-icons_2e83ff_256x240.png" server="172.18.0.178//var/www/it_atenea/" local="129773368460323732" remote="129895236280000000" />
<file name="ui-icons_454545_256x240.png" server="172.18.0.178//var/www/it_atenea/" local="129773368460403668" remote="129895236280000000" />
<file name="ui-icons_888888_256x240.png" server="172.18.0.178//var/www/it_atenea/" local="129773368460453628" remote="129895236280000000" />
<file name="ui-icons_cd0a0a_256x240.png" server="172.18.0.178//var/www/it_atenea/" local="129773368460493596" remote="129895236280000000" />
<file name="ui-bg_flat_0_aaaaaa_40x100.png" server="172.18.0.111//var/www/contratacion_2013/" local="129773368459744196" remote="129980677960000000" />
<file name="ui-bg_glass_55_fbf9ee_1x400.png" server="172.18.0.111//var/www/contratacion_2013/" local="129773368459794156" remote="129980677960000000" />
<file name="ui-bg_glass_65_ffffff_1x400.png" server="172.18.0.111//var/www/contratacion_2013/" local="129773368459874092" remote="129980677960000000" />
<file name="ui-bg_glass_75_dadada_1x400.png" server="172.18.0.111//var/www/contratacion_2013/" local="129773368459914060" remote="129980677960000000" />
<file name="ui-bg_glass_75_e6e6e6_1x400.png" server="172.18.0.111//var/www/contratacion_2013/" local="129773368459954028" remote="129980677960000000" />
<file name="ui-bg_glass_75_ffffff_1x400.png" server="172.18.0.111//var/www/contratacion_2013/" local="129773368459993996" remote="129980677960000000" />
<file name="ui-bg_highlight-soft_75_cccccc_1x100.png" server="172.18.0.111//var/www/contratacion_2013/" local="129773368460023972" remote="129980677960000000" />
<file name="ui-bg_inset-soft_95_fef1ec_1x100.png" server="172.18.0.111//var/www/contratacion_2013/" local="129773368460063940" remote="129980677970000000" />
<file name="ui-icons_222222_256x240.png" server="172.18.0.111//var/www/contratacion_2013/" local="129773368460283764" remote="129980677970000000" />
<file name="ui-icons_2e83ff_256x240.png" server="172.18.0.111//var/www/contratacion_2013/" local="129773368460323732" remote="129980677970000000" />
<file name="ui-icons_454545_256x240.png" server="172.18.0.111//var/www/contratacion_2013/" local="129773368460403668" remote="129980677970000000" />
<file name="ui-icons_888888_256x240.png" server="172.18.0.111//var/www/contratacion_2013/" local="129773368460453628" remote="129980677970000000" />
<file name="ui-icons_cd0a0a_256x240.png" server="172.18.0.111//var/www/contratacion_2013/" local="129773368460493596" remote="129980677970000000" />
<file name="ui-bg_flat_0_aaaaaa_40x100.png" server="172.18.0.27//trabajosrv/aplicaciones/www/Produccion_Nacional_2012/Administrador/" local="129773368459744196" remote="130173416090000000" />
<file name="ui-bg_glass_55_fbf9ee_1x400.png" server="172.18.0.27//trabajosrv/aplicaciones/www/Produccion_Nacional_2012/Administrador/" local="129773368459794156" remote="130173416090000000" />
<file name="ui-bg_glass_65_ffffff_1x400.png" server="172.18.0.27//trabajosrv/aplicaciones/www/Produccion_Nacional_2012/Administrador/" local="129773368459874092" remote="130173416090000000" />
<file name="ui-bg_glass_75_dadada_1x400.png" server="172.18.0.27//trabajosrv/aplicaciones/www/Produccion_Nacional_2012/Administrador/" local="129773368459914060" remote="130173416090000000" />
<file name="ui-bg_glass_75_e6e6e6_1x400.png" server="172.18.0.27//trabajosrv/aplicaciones/www/Produccion_Nacional_2012/Administrador/" local="129773368459954028" remote="130173416100000000" />
<file name="ui-bg_glass_75_ffffff_1x400.png" server="172.18.0.27//trabajosrv/aplicaciones/www/Produccion_Nacional_2012/Administrador/" local="129773368459993996" remote="130173416100000000" />
<file name="ui-bg_highlight-soft_75_cccccc_1x100.png" server="172.18.0.27//trabajosrv/aplicaciones/www/Produccion_Nacional_2012/Administrador/" local="129773368460023972" remote="130173416140000000" />
<file name="ui-bg_inset-soft_95_fef1ec_1x100.png" server="172.18.0.27//trabajosrv/aplicaciones/www/Produccion_Nacional_2012/Administrador/" local="129773368460063940" remote="130173416140000000" />
<file name="ui-icons_222222_256x240.png" server="172.18.0.27//trabajosrv/aplicaciones/www/Produccion_Nacional_2012/Administrador/" local="129773368460283764" remote="130173416140000000" />
<file name="ui-icons_2e83ff_256x240.png" server="172.18.0.27//trabajosrv/aplicaciones/www/Produccion_Nacional_2012/Administrador/" local="129773368460323732" remote="130173416140000000" />
<file name="ui-icons_454545_256x240.png" server="172.18.0.27//trabajosrv/aplicaciones/www/Produccion_Nacional_2012/Administrador/" local="129773368460403668" remote="130173416140000000" />
<file name="ui-icons_888888_256x240.png" server="172.18.0.27//trabajosrv/aplicaciones/www/Produccion_Nacional_2012/Administrador/" local="129773368460453628" remote="130173416150000000" />
<file name="ui-icons_cd0a0a_256x240.png" server="172.18.0.27//trabajosrv/aplicaciones/www/Produccion_Nacional_2012/Administrador/" local="129773368460493596" remote="130173416150000000" />
<file name="ui-bg_flat_0_aaaaaa_40x100.png" server="172.18.0.125//AplicacionesMcit/www/html/contratos/" local="129773368459744196" remote="130281844840000000" />
<file name="ui-bg_glass_55_fbf9ee_1x400.png" server="172.18.0.125//AplicacionesMcit/www/html/contratos/" local="129773368459794156" remote="130281844840000000" />
<file name="ui-bg_glass_65_ffffff_1x400.png" server="172.18.0.125//AplicacionesMcit/www/html/contratos/" local="129773368459874092" remote="130281844840000000" />
<file name="ui-bg_glass_75_dadada_1x400.png" server="172.18.0.125//AplicacionesMcit/www/html/contratos/" local="129773368459914060" remote="130281844840000000" />
<file name="ui-bg_glass_75_e6e6e6_1x400.png" server="172.18.0.125//AplicacionesMcit/www/html/contratos/" local="129773368459954028" remote="130281844840000000" />
<file name="ui-bg_glass_75_ffffff_1x400.png" server="172.18.0.125//AplicacionesMcit/www/html/contratos/" local="129773368459993996" remote="130281844840000000" />
<file name="ui-bg_highlight-soft_75_cccccc_1x100.png" server="172.18.0.125//AplicacionesMcit/www/html/contratos/" local="129773368460023972" remote="130281844840000000" />
<file name="ui-bg_inset-soft_95_fef1ec_1x100.png" server="172.18.0.125//AplicacionesMcit/www/html/contratos/" local="129773368460063940" remote="130281844840000000" />
<file name="ui-icons_222222_256x240.png" server="172.18.0.125//AplicacionesMcit/www/html/contratos/" local="129773368460283764" remote="130281844840000000" />
<file name="ui-icons_2e83ff_256x240.png" server="172.18.0.125//AplicacionesMcit/www/html/contratos/" local="129773368460323732" remote="130281844840000000" />
<file name="ui-icons_454545_256x240.png" server="172.18.0.125//AplicacionesMcit/www/html/contratos/" local="129773368460403668" remote="130281844840000000" />
<file name="ui-icons_888888_256x240.png" server="172.18.0.125//AplicacionesMcit/www/html/contratos/" local="129773368460453628" remote="130281844840000000" />
<file name="ui-icons_cd0a0a_256x240.png" server="172.18.0.125//AplicacionesMcit/www/html/contratos/" local="129773368460493596" remote="130281844840000000" />
</dwsync>