<?xml version="1.0" encoding="utf-8" ?>
<dwsync>
<file name="collapsible.html" server="172.18.0.178//var/www/mcit_th/" local="129773368411472844" remote="129773380660000000" />
<file name="custom-icons.html" server="172.18.0.178//var/www/mcit_th/" local="129773368411672684" remote="129773380830000000" />
<file name="default.html" server="172.18.0.178//var/www/mcit_th/" local="129773368411872524" remote="129773372760000000" />
<file name="fillspace.html" server="172.18.0.178//var/www/mcit_th/" local="129773368412062372" remote="129773381090000000" />
<file name="hoverintent.html" server="172.18.0.178//var/www/mcit_th/" local="129773377278997079" remote="129773381460000000" />
<file name="index.html" server="172.18.0.178//var/www/mcit_th/" local="129773368412452060" remote="129773372760000000" />
<file name="mouseover.html" server="172.18.0.178//var/www/mcit_th/" local="129773368412621924" remote="129773372760000000" />
<file name="no-auto-height.html" server="172.18.0.178//var/www/mcit_th/" local="129773368412811772" remote="129773372760000000" />
<file name="sortable.html" server="172.18.0.178//var/www/mcit_th/" local="129773368413001620" remote="129773372760000000" />
<file name="collapsible.html" server="172.18.0.111//var/www/servicios/" local="129773368411472844" remote="129827749110000000" />
<file name="custom-icons.html" server="172.18.0.111//var/www/servicios/" local="129773368411672684" remote="129827749110000000" />
<file name="default.html" server="172.18.0.111//var/www/servicios/" local="129773368411872524" remote="129827749110000000" />
<file name="fillspace.html" server="172.18.0.111//var/www/servicios/" local="129773368412062372" remote="129827749110000000" />
<file name="hoverintent.html" server="172.18.0.111//var/www/servicios/" local="129773377278997079" remote="129827749110000000" />
<file name="index.html" server="172.18.0.111//var/www/servicios/" local="129773368412452060" remote="129828720690000000" />
<file name="mouseover.html" server="172.18.0.111//var/www/servicios/" local="129773368412621924" remote="129827749110000000" />
<file name="no-auto-height.html" server="172.18.0.111//var/www/servicios/" local="129773368412811772" remote="129827749110000000" />
<file name="sortable.html" server="172.18.0.111//var/www/servicios/" local="129773368413001620" remote="129827749110000000" />
<file name="collapsible.html" server="172.18.0.178//var/www/it_atenea/" local="129773368411472844" remote="129895236180000000" />
<file name="custom-icons.html" server="172.18.0.178//var/www/it_atenea/" local="129773368411672684" remote="129895236190000000" />
<file name="default.html" server="172.18.0.178//var/www/it_atenea/" local="129773368411872524" remote="129895236190000000" />
<file name="fillspace.html" server="172.18.0.178//var/www/it_atenea/" local="129773368412062372" remote="129895236190000000" />
<file name="hoverintent.html" server="172.18.0.178//var/www/it_atenea/" local="129773377278997079" remote="129895236200000000" />
<file name="index.html" server="172.18.0.178//var/www/it_atenea/" local="129773368412452060" remote="129895236200000000" />
<file name="mouseover.html" server="172.18.0.178//var/www/it_atenea/" local="129773368412621924" remote="129895236200000000" />
<file name="no-auto-height.html" server="172.18.0.178//var/www/it_atenea/" local="129773368412811772" remote="129895236200000000" />
<file name="sortable.html" server="172.18.0.178//var/www/it_atenea/" local="129773368413001620" remote="129895236200000000" />
<file name="collapsible.html" server="172.18.0.111//var/www/contratacion_2013/" local="129773368411472844" remote="129980677470000000" />
<file name="custom-icons.html" server="172.18.0.111//var/www/contratacion_2013/" local="129773368411672684" remote="129980677530000000" />
<file name="default.html" server="172.18.0.111//var/www/contratacion_2013/" local="129773368411872524" remote="129980677530000000" />
<file name="fillspace.html" server="172.18.0.111//var/www/contratacion_2013/" local="129773368412062372" remote="129980677530000000" />
<file name="hoverintent.html" server="172.18.0.111//var/www/contratacion_2013/" local="129773377278997079" remote="129980677570000000" />
<file name="index.html" server="172.18.0.111//var/www/contratacion_2013/" local="129773368412452060" remote="129980677590000000" />
<file name="mouseover.html" server="172.18.0.111//var/www/contratacion_2013/" local="129773368412621924" remote="129980677590000000" />
<file name="no-auto-height.html" server="172.18.0.111//var/www/contratacion_2013/" local="129773368412811772" remote="129980677590000000" />
<file name="sortable.html" server="172.18.0.111//var/www/contratacion_2013/" local="129773368413001620" remote="129980677610000000" />
<file name="collapsible.html" server="172.18.0.27//trabajosrv/aplicaciones/www/Produccion_Nacional_2012/Administrador/" local="129773368411472844" remote="130173415270000000" />
<file name="custom-icons.html" server="172.18.0.27//trabajosrv/aplicaciones/www/Produccion_Nacional_2012/Administrador/" local="129773368411672684" remote="130173415390000000" />
<file name="default.html" server="172.18.0.27//trabajosrv/aplicaciones/www/Produccion_Nacional_2012/Administrador/" local="129773368411872524" remote="130173415400000000" />
<file name="fillspace.html" server="172.18.0.27//trabajosrv/aplicaciones/www/Produccion_Nacional_2012/Administrador/" local="129773368412062372" remote="130173415400000000" />
<file name="hoverintent.html" server="172.18.0.27//trabajosrv/aplicaciones/www/Produccion_Nacional_2012/Administrador/" local="129773377278997079" remote="130173415410000000" />
<file name="index.html" server="172.18.0.27//trabajosrv/aplicaciones/www/Produccion_Nacional_2012/Administrador/" local="129773368412452060" remote="130173415410000000" />
<file name="mouseover.html" server="172.18.0.27//trabajosrv/aplicaciones/www/Produccion_Nacional_2012/Administrador/" local="129773368412621924" remote="130173415410000000" />
<file name="no-auto-height.html" server="172.18.0.27//trabajosrv/aplicaciones/www/Produccion_Nacional_2012/Administrador/" local="129773368412811772" remote="130173415410000000" />
<file name="sortable.html" server="172.18.0.27//trabajosrv/aplicaciones/www/Produccion_Nacional_2012/Administrador/" local="129773368413001620" remote="130173415420000000" />
<file name="collapsible.html" server="172.18.0.125//AplicacionesMcit/www/html/contratos/" local="129773368411472844" remote="130281844670000000" />
<file name="custom-icons.html" server="172.18.0.125//AplicacionesMcit/www/html/contratos/" local="129773368411672684" remote="130281844690000000" />
<file name="default.html" server="172.18.0.125//AplicacionesMcit/www/html/contratos/" local="129773368411872524" remote="130281844690000000" />
<file name="fillspace.html" server="172.18.0.125//AplicacionesMcit/www/html/contratos/" local="129773368412062372" remote="130281844690000000" />
<file name="hoverintent.html" server="172.18.0.125//AplicacionesMcit/www/html/contratos/" local="129773377278997079" remote="130281844690000000" />
<file name="index.html" server="172.18.0.125//AplicacionesMcit/www/html/contratos/" local="129773368412452060" remote="130281844690000000" />
<file name="mouseover.html" server="172.18.0.125//AplicacionesMcit/www/html/contratos/" local="129773368412621924" remote="130281844690000000" />
<file name="no-auto-height.html" server="172.18.0.125//AplicacionesMcit/www/html/contratos/" local="129773368412811772" remote="130281844690000000" />
<file name="sortable.html" server="172.18.0.125//AplicacionesMcit/www/html/contratos/" local="129773368413001620" remote="130281844690000000" />
</dwsync>